media/take5.mp4
src/spotify_mcp/__init__.py
src/spotify_mcp/server.py
src/spotify_mcp/spotify_api.py
src/spotify_mcp/utils.py
orange_spotify_mcp-0.2.0.dist-info/METADATA
orange_spotify_mcp-0.2.0.dist-info/WHEEL
orange_spotify_mcp-0.2.0.dist-info/entry_points.txt
orange_spotify_mcp-0.2.0.dist-info/RECORD
